<annotation>
	<folder>chequeOutput</folder>
	<filename>New Business_IA0040897_Cheque-Demand draft copy.jpg</filename>
	<path>D:\Semester VIII\Future Generali\chequeOutput\New Business_IA0040897_Cheque-Demand draft copy.jpg</path>
	<source>
		<database>Unknown</database>
	</source>
	<size>
		<width>1440</width>
		<height>1080</height>
		<depth>3</depth>
	</size>
	<segmented>0</segmented>
	<object>
		<name>bank_name</name>
		<pose>Unspecified</pose>
		<truncated>0</truncated>
		<difficult>0</difficult>
		<bndbox>
			<xmin>151</xmin>
			<ymin>292</ymin>
			<xmax>341</xmax>
			<ymax>359</ymax>
		</bndbox>
	</object>
	<object>
		<name>date</name>
		<pose>Unspecified</pose>
		<truncated>0</truncated>
		<difficult>0</difficult>
		<bndbox>
			<xmin>1075</xmin>
			<ymin>308</ymin>
			<xmax>1364</xmax>
			<ymax>365</ymax>
		</bndbox>
	</object>
	<object>
		<name>amount</name>
		<pose>Unspecified</pose>
		<truncated>0</truncated>
		<difficult>0</difficult>
		<bndbox>
			<xmin>1077</xmin>
			<ymin>489</ymin>
			<xmax>1279</xmax>
			<ymax>552</ymax>
		</bndbox>
	</object>
	<object>
		<name>account_no</name>
		<pose>Unspecified</pose>
		<truncated>0</truncated>
		<difficult>0</difficult>
		<bndbox>
			<xmin>198</xmin>
			<ymin>558</ymin>
			<xmax>474</xmax>
			<ymax>612</ymax>
		</bndbox>
	</object>
	<object>
		<name>customer_name</name>
		<pose>Unspecified</pose>
		<truncated>0</truncated>
		<difficult>0</difficult>
		<bndbox>
			<xmin>1158</xmin>
			<ymin>687</ymin>
			<xmax>1358</xmax>
			<ymax>751</ymax>
		</bndbox>
	</object>
	<object>
		<name>micr_code</name>
		<pose>Unspecified</pose>
		<truncated>0</truncated>
		<difficult>0</difficult>
		<bndbox>
			<xmin>340</xmin>
			<ymin>794</ymin>
			<xmax>788</xmax>
			<ymax>871</ymax>
		</bndbox>
	</object>
</annotation>
