<annotation>
	<folder>chequeOutput</folder>
	<filename>New Business_IA0050308_Cheque-Demand draft copy.jpg</filename>
	<path>D:\Semester VIII\Future Generali\chequeOutput\New Business_IA0050308_Cheque-Demand draft copy.jpg</path>
	<source>
		<database>Unknown</database>
	</source>
	<size>
		<width>780</width>
		<height>1040</height>
		<depth>3</depth>
	</size>
	<segmented>0</segmented>
	<object>
		<name>bank_name</name>
		<pose>Unspecified</pose>
		<truncated>0</truncated>
		<difficult>0</difficult>
		<bndbox>
			<xmin>534</xmin>
			<ymin>211</ymin>
			<xmax>577</xmax>
			<ymax>258</ymax>
		</bndbox>
	</object>
	<object>
		<name>date</name>
		<pose>Unspecified</pose>
		<truncated>0</truncated>
		<difficult>0</difficult>
		<bndbox>
			<xmin>536</xmin>
			<ymin>711</ymin>
			<xmax>566</xmax>
			<ymax>942</ymax>
		</bndbox>
	</object>
	<object>
		<name>amount</name>
		<pose>Unspecified</pose>
		<truncated>0</truncated>
		<difficult>0</difficult>
		<bndbox>
			<xmin>407</xmin>
			<ymin>768</ymin>
			<xmax>443</xmax>
			<ymax>909</ymax>
		</bndbox>
	</object>
	<object>
		<name>customer_name</name>
		<pose>Unspecified</pose>
		<truncated>0</truncated>
		<difficult>0</difficult>
		<bndbox>
			<xmin>352</xmin>
			<ymin>307</ymin>
			<xmax>384</xmax>
			<ymax>579</ymax>
		</bndbox>
	</object>
	<object>
		<name>micr_code</name>
		<pose>Unspecified</pose>
		<truncated>0</truncated>
		<difficult>0</difficult>
		<bndbox>
			<xmin>194</xmin>
			<ymin>291</ymin>
			<xmax>230</xmax>
			<ymax>573</ymax>
		</bndbox>
	</object>
</annotation>
