<annotation>
	<folder>chequeOutput</folder>
	<filename>New Business_IA0051530_Cheque-Demand draft copy.jpg</filename>
	<path>C:\Users\ishag\Desktop\chequeOutput\New Business_IA0051530_Cheque-Demand draft copy.jpg</path>
	<source>
		<database>Unknown</database>
	</source>
	<size>
		<width>2270</width>
		<height>1605</height>
		<depth>3</depth>
	</size>
	<segmented>0</segmented>
	<object>
		<name>bank_name</name>
		<pose>Unspecified</pose>
		<truncated>0</truncated>
		<difficult>0</difficult>
		<bndbox>
			<xmin>1610</xmin>
			<ymin>984</ymin>
			<xmax>1642</xmax>
			<ymax>1154</ymax>
		</bndbox>
	</object>
	<object>
		<name>date</name>
		<pose>Unspecified</pose>
		<truncated>0</truncated>
		<difficult>0</difficult>
		<bndbox>
			<xmin>1609</xmin>
			<ymin>108</ymin>
			<xmax>1659</xmax>
			<ymax>423</ymax>
		</bndbox>
	</object>
	<object>
		<name>amount</name>
		<pose>Unspecified</pose>
		<truncated>0</truncated>
		<difficult>0</difficult>
		<bndbox>
			<xmin>1808</xmin>
			<ymin>190</ymin>
			<xmax>1872</xmax>
			<ymax>423</ymax>
		</bndbox>
	</object>
	<object>
		<name>account_no</name>
		<pose>Unspecified</pose>
		<truncated>0</truncated>
		<difficult>0</difficult>
		<bndbox>
			<xmin>1913</xmin>
			<ymin>1152</ymin>
			<xmax>1963</xmax>
			<ymax>1420</ymax>
		</bndbox>
	</object>
	<object>
		<name>micr_code</name>
		<pose>Unspecified</pose>
		<truncated>0</truncated>
		<difficult>0</difficult>
		<bndbox>
			<xmin>2155</xmin>
			<ymin>734</ymin>
			<xmax>2242</xmax>
			<ymax>1214</ymax>
		</bndbox>
	</object>
	<object>
		<name>customer_name</name>
		<pose>Unspecified</pose>
		<truncated>0</truncated>
		<difficult>0</difficult>
		<bndbox>
			<xmin>1895</xmin>
			<ymin>108</ymin>
			<xmax>1942</xmax>
			<ymax>324</ymax>
		</bndbox>
	</object>
</annotation>
